finx_option_pricer/__init__.py
finx_option_pricer/bsm.py
finx_option_pricer/calcs.py
finx_option_pricer/option.py
finx_option_pricer/option_plot.py
finx_option_pricer/option_structures.py
finx_option_pricer-0.3.0.dist-info/LICENSE
finx_option_pricer-0.3.0.dist-info/METADATA
finx_option_pricer-0.3.0.dist-info/WHEEL
finx_option_pricer-0.3.0.dist-info/top_level.txt
finx_option_pricer-0.3.0.dist-info/RECORD
