Metadata-Version: 2.1
Name: finx-option-pricer
Version: 0.3.0
Summary: Option pricer and visualizer
Home-page: https://github.com/westonplatter/finx-option-pricer
Author: Weston Platter
Author-email: westonplatter+finx@gmail.com
License: BSD-3
Project-URL: Issue Tracker, https://github.com/westonplatter/finx-option-pricer/issues
Project-URL: Source Code, https://github.com/westonplatter/finx-option-pricer
Platform: UNKNOWN
Requires-Python: >=3.6
License-File: LICENSE
Requires-Dist: dash-daq
Requires-Dist: loguru
Requires-Dist: pandas (<1.4,>=1.3.0)
Requires-Dist: matplotlib
Requires-Dist: numpy
Requires-Dist: pydantic
Requires-Dist: scipy
Provides-Extra: dev
Requires-Dist: ipdb ; extra == 'dev'
Requires-Dist: click ; extra == 'dev'
Requires-Dist: matplotlib ; extra == 'dev'
Requires-Dist: twine ; extra == 'dev'
Requires-Dist: jupyterlab ; extra == 'dev'
Requires-Dist: jupyterlab-dash ; extra == 'dev'
Requires-Dist: jupyter-dash ; extra == 'dev'
Requires-Dist: nbstripout ; extra == 'dev'
Requires-Dist: plotly ; extra == 'dev'
Provides-Extra: test
Requires-Dist: pytest ; extra == 'test'
